tsengmodtool/__init__.py
tsengmodtool/__main__.py
tsengmodtool-3.0.4.dist-info/METADATA
tsengmodtool-3.0.4.dist-info/WHEEL
tsengmodtool-3.0.4.dist-info/top_level.txt
tsengmodtool-3.0.4.dist-info/RECORD
