Metadata-Version: 2.4
Name: tsengmodtool
Version: 3.0.4
Summary: 完整中文版《貓咪大戰爭》存檔修改工具，林安潔製作
Dynamic: summary
